wst_api_client/__init__.py
wst_api_client/api_client.py
wst_api_client/api_response.py
wst_api_client/configuration.py
wst_api_client/exceptions.py
wst_api_client/py.typed
wst_api_client/rest.py
wst_api_client/api/__init__.py
wst_api_client/api/assets_api.py
wst_api_client/api/incident_api.py
wst_api_client/api/map_api.py
wst_api_client/api/metadata_api.py
wst_api_client/api/situation_api.py
wst_api_client/models/__init__.py
wst_api_client/models/additional_information.py
wst_api_client/models/detour.py
wst_api_client/models/incident.py
wst_api_client/models/incident_state.py
wst_api_client/models/inline_object.py
wst_api_client/models/inline_object1.py
wst_api_client/models/inline_object1_nl.py
wst_api_client/models/inline_object1_nl_alternative.py
wst_api_client/models/inline_object1_nl_alternative_from.py
wst_api_client/models/inline_object1_nl_channel.py
wst_api_client/models/inline_object1_nl_direction.py
wst_api_client/models/inline_object1_nl_extra_travel_time.py
wst_api_client/models/inline_object1_nl_incidents.py
wst_api_client/models/inline_object1_nl_incidents_extra_travel_time.py
wst_api_client/models/inline_object1_nl_incidents_no_incidents.py
wst_api_client/models/inline_object1_nl_road.py
wst_api_client/models/inline_object1_nl_status.py
wst_api_client/models/inline_object1_nl_status_state.py
wst_api_client/models/inline_object1_nl_subscription_group.py
wst_api_client/models/inline_object1_nl_widget.py
wst_api_client/models/inline_object_date.py
wst_api_client/models/inline_object_detour.py
wst_api_client/models/inline_object_incident_popup.py
wst_api_client/models/inline_object_incident_popup_error.py
wst_api_client/models/inline_object_incident_popup_title.py
wst_api_client/models/inline_object_incident_popup_title_error.py
wst_api_client/models/inline_object_incident_status_timeline.py
wst_api_client/models/inline_object_navigation.py
wst_api_client/models/inline_object_scheduled_incidents.py
wst_api_client/models/inline_object_situation_map.py
wst_api_client-0.0.1.dist-info/METADATA
wst_api_client-0.0.1.dist-info/WHEEL
wst_api_client-0.0.1.dist-info/top_level.txt
wst_api_client-0.0.1.dist-info/RECORD
